ra_flatfile_importer/__init__.py
ra_flatfile_importer/__main__.py
ra_flatfile_importer/cli.py
ra_flatfile_importer/models.py
ra_flatfile_importer/uploader.py
ra_flatfile_importer/util.py
ra_flatfile_importer-2.1.1.dist-info/LICENSES/MPL-2.0.txt
ra_flatfile_importer-2.1.1.dist-info/LICENSES/MIT.txt
ra_flatfile_importer-2.1.1.dist-info/WHEEL
ra_flatfile_importer-2.1.1.dist-info/METADATA
ra_flatfile_importer-2.1.1.dist-info/RECORD
