Metadata-Version: 2.1
Name: ra-flatfile-importer
Version: 2.1.1
Summary: Flatfile importer for OS2mo
Home-page: https://magenta.dk/
License: MPL-2.0
Keywords: os2mo
Author: Magenta
Author-email: info@magenta.dk
Requires-Python: >=3.9,<4.0
Classifier: License :: OSI Approved
Classifier: Programming Language :: Python :: 3
Classifier: Programming Language :: Python :: 3.10
Classifier: Programming Language :: Python :: 3.9
Requires-Dist: click (>=8.0.3,<9.0.0)
Requires-Dist: pydantic (>=1.9.0,<2.0.0)
Requires-Dist: ra-utils (>=0.4.0,<0.5.0)
Requires-Dist: raclients (>=1.2.1,<2.0.0)
Requires-Dist: ramodels (>=5.3.2,<6.0.0)
Requires-Dist: tqdm (>=4.60.0,<5.0.0)
Project-URL: Repository, https://git.magenta.dk/rammearkitektur/ra-flatfile-importer
